boombox/__init__.py
boombox/boombox.py
boombox/endpoints.py
boombox/typed.py
boombox/__pycache__/__init__.cpython-311.pyc
boombox/__pycache__/__init__.cpython-313.pyc
boombox/__pycache__/boombox.cpython-311.pyc
boombox/__pycache__/boombox.cpython-313.pyc
boombox/__pycache__/endpoints.cpython-311.pyc
boombox/__pycache__/typed.cpython-311.pyc
boombox/_vendor/pyrlang/LICENSE
boombox/_vendor/pyrlang/__init__.py
boombox/_vendor/pyrlang/errors.py
boombox/_vendor/pyrlang/match.py
boombox/_vendor/pyrlang/net_kernel.py
boombox/_vendor/pyrlang/node.py
boombox/_vendor/pyrlang/node_db.py
boombox/_vendor/pyrlang/notebook.py
boombox/_vendor/pyrlang/process.py
boombox/_vendor/pyrlang/rex.py
boombox/_vendor/pyrlang/util.py
boombox/_vendor/pyrlang/__pycache__/__init__.cpython-311.pyc
boombox/_vendor/pyrlang/__pycache__/errors.cpython-311.pyc
boombox/_vendor/pyrlang/__pycache__/match.cpython-311.pyc
boombox/_vendor/pyrlang/__pycache__/net_kernel.cpython-311.pyc
boombox/_vendor/pyrlang/__pycache__/node.cpython-311.pyc
boombox/_vendor/pyrlang/__pycache__/node_db.cpython-311.pyc
boombox/_vendor/pyrlang/__pycache__/notebook.cpython-311.pyc
boombox/_vendor/pyrlang/__pycache__/process.cpython-311.pyc
boombox/_vendor/pyrlang/__pycache__/rex.cpython-311.pyc
boombox/_vendor/pyrlang/__pycache__/util.cpython-311.pyc
boombox/_vendor/pyrlang/dist_proto/__init__.py
boombox/_vendor/pyrlang/dist_proto/base_dist_protocol.py
boombox/_vendor/pyrlang/dist_proto/client.py
boombox/_vendor/pyrlang/dist_proto/distribution.py
boombox/_vendor/pyrlang/dist_proto/epmd_client.py
boombox/_vendor/pyrlang/dist_proto/flags.py
boombox/_vendor/pyrlang/dist_proto/server.py
boombox/_vendor/pyrlang/dist_proto/version.py
boombox/_vendor/pyrlang/dist_proto/__pycache__/__init__.cpython-311.pyc
boombox/_vendor/pyrlang/dist_proto/__pycache__/base_dist_protocol.cpython-311.pyc
boombox/_vendor/pyrlang/dist_proto/__pycache__/client.cpython-311.pyc
boombox/_vendor/pyrlang/dist_proto/__pycache__/distribution.cpython-311.pyc
boombox/_vendor/pyrlang-0.12a0-py3.11.egg-info/PKG-INFO
boombox/_vendor/pyrlang-0.12a0-py3.11.egg-info/SOURCES.txt
boombox/_vendor/pyrlang-0.12a0-py3.11.egg-info/dependency_links.txt
boombox/_vendor/pyrlang-0.12a0-py3.11.egg-info/installed-files.txt
boombox/_vendor/pyrlang-0.12a0-py3.11.egg-info/requires.txt
boombox/_vendor/pyrlang-0.12a0-py3.11.egg-info/top_level.txt
boombox/_vendor/pyrlang_term-1.5a0.dist-info/licenses/LICENSE
membrane_boombox-0.1.0.dist-info/licenses/LICENSE
boombox/_vendor/pyrlang_term-1.5a0.dist-info/INSTALLER
boombox/_vendor/pyrlang_term-1.5a0.dist-info/METADATA
boombox/_vendor/pyrlang_term-1.5a0.dist-info/RECORD
boombox/_vendor/pyrlang_term-1.5a0.dist-info/REQUESTED
boombox/_vendor/pyrlang_term-1.5a0.dist-info/WHEEL
boombox/_vendor/pyrlang_term-1.5a0.dist-info/direct_url.json
boombox/_vendor/pyrlang_term-1.5a0.dist-info/top_level.txt
membrane_boombox-0.1.0.dist-info/METADATA
membrane_boombox-0.1.0.dist-info/WHEEL
membrane_boombox-0.1.0.dist-info/top_level.txt
membrane_boombox-0.1.0.dist-info/RECORD
