Metadata-Version: 2.4
Name: membrane_boombox
Version: 0.1.0
Summary: Boombox SDK for Python
Author: Membrane Team
License-Expression: Apache-2.0
Requires-Python: >=3.11
License-File: LICENSE
Requires-Dist: numpy>=2.2.5
Requires-Dist: typing-extensions<5,>=4.13.2
Dynamic: license-file
